fractalgebra/__init__.py
fractalgebra/helpers/__init__.py
fractalgebra/helpers/calculator.py
fractalgebra/helpers/errors.py
fractalgebra/helpers/main_helper.py
fractalgebra/helpers/rational_number.py
fractalgebra/main.py
fractalgebra-0.1.4.dist-info/entry_points.txt
fractalgebra-0.1.4.dist-info/WHEEL
fractalgebra-0.1.4.dist-info/METADATA
fractalgebra-0.1.4.dist-info/RECORD
