Metadata-Version: 2.1
Name: fractalgebra
Version: 0.1.4
Summary: a simple fractions calculator
Home-page: https://github.com/bookRa/fractalgebra
License: MIT
Keywords: poetry,typer,math
Author: bookRa
Author-email: omar.abdelbadie1@gmail.com
Requires-Python: >=3.8,<4.0
Classifier: Development Status :: 3 - Alpha
Classifier: Environment :: Console
Classifier: License :: OSI Approved :: MIT License
Classifier: Operating System :: OS Independent
Classifier: Programming Language :: Python :: 3
Classifier: Programming Language :: Python :: 3.10
Classifier: Programming Language :: Python :: 3.8
Classifier: Programming Language :: Python :: 3.9
Requires-Dist: typer (>=0.4.0,<0.5.0)
Project-URL: Repository, https://github.com/bookRa/fractalgebra
